Workbook

Sheet Restaurantes
A1: # | B1: Prioridad | C1: Restaurante | D1: Ciudad | E1: Zona | F1: Tipo | G1: Teléfono | H1: Línea | I1: WhatsApp | J1: Dirección | K1: Estado | L1: Primer contacto | M1: Seguimiento | N1: Plan de interés | O1: Mensualidad | P1: Próxima acción | Q1: Notas | R1: Pedidos por WhatsApp | S1: Fuente
A2: 1 | B2: Alta | C2: A Otro Nivel Parrilla | D2: Bello | F2: Parrilla / comida rápida | G2: 3105435674 | H2: =IF(G2="","Sin número",IF(LEFT(G2,1)="3","Celular","Fijo")) -> Celular | I2: =IF(H2="Celular",HYPERLINK("https://wa.me/57"&G2,"Abrir chat"),"") -> Abrir chat | J2: Cl 57 # 67B-79 | K2: Por contactar | M2: =IF(L2="","",L2+4) | O2: =IF(N2="","",INDEX(Planes!$B$4:$B$6,MATCH(N2,Planes!$A$4:$A$6,0))) | P2: Enviar mensaje 1b | R2: Menú en línea con pedidos a WhatsApp (ola.click) | S2: =HYPERLINK("https://aotronivelparrilla.ola.click/","Ver fuente") -> Ver fuente
A3: 2 | B3: Alta | C3: Aquí Fue Trapiche | D3: Bello | F3: Restaurante | G3: 3224852584 | H3: =IF(G3="","Sin número",IF(LEFT(G3,1)="3","Celular","Fijo")) -> Celular | I3: =IF(H3="Celular",HYPERLINK("https://wa.me/57"&G3,"Abrir chat"),"") -> Abrir chat | J3: Cra 66 # 57-46 | K3: Por contactar | M3: =IF(L3="","",L3+4) | O3: =IF(N3="","",INDEX(Planes!$B$4:$B$6,MATCH(N3,Planes!$A$4:$A$6,0))) | P3: Enviar mensaje 1b | R3: Menú en línea con pedidos a WhatsApp (ola.click) | S3: =HYPERLINK("https://aquifuedomicilio.ola.click/","Ver fuente") -> Ver fuente
A4: 3 | B4: Alta | C4: Arroz Caracas | D4: Bello | F4: Comida china | H4: =IF(G4="","Sin número",IF(LEFT(G4,1)="3","Celular","Fijo")) -> Sin número | I4: =IF(H4="Celular",HYPERLINK("https://wa.me/57"&G4,"Abrir chat"),"") | K4: Por contactar | M4: =IF(L4="","",L4+4) | O4: =IF(N4="","",INDEX(Planes!$B$4:$B$6,MATCH(N4,Planes!$A$4:$A$6,0))) | P4: Escribir por el botón de WhatsApp de su menú en línea | R4: Menú en línea con pedidos a WhatsApp; reparte en Cabañas, París y Santa Ana (ola.click) | S4: =HYPERLINK("https://arroz-caracas.ola.click/info","Ver fuente") -> Ver fuente
A5: 4 | B5: Alta | C5: Carnes al Carbón Valadares | D5: Bello | F5: Asados | H5: =IF(G5="","Sin número",IF(LEFT(G5,1)="3","Celular","Fijo")) -> Sin número | I5: =IF(H5="Celular",HYPERLINK("https://wa.me/57"&G5,"Abrir chat"),"") | J5: Cra 66BB # 57A-34 | K5: Por contactar | M5: =IF(L5="","",L5+4) | O5: =IF(N5="","",INDEX(Planes!$B$4:$B$6,MATCH(N5,Planes!$A$4:$A$6,0))) | P5: Escribir por el botón de WhatsApp de su menú en línea | R5: Menú en línea con pedidos a WhatsApp (ola.click) | S5: =HYPERLINK("https://carnesalcarbonvaladares.ola.click/","Ver fuente") -> Ver fuente
A6: 5 | B6: Alta | C6: Family Restorant Bar & Grill | D6: Bello | E6: Andalucía | F6: Hamburguesas / parrilla | G6: 3232803762 | H6: =IF(G6="","Sin número",IF(LEFT(G6,1)="3","Celular","Fijo")) -> Celular | I6: =IF(H6="Celular",HYPERLINK("https://wa.me/57"&G6,"Abrir chat"),"") -> Abrir chat | J6: Cl 55 # 52-26 | K6: Por contactar | M6: =IF(L6="","",L6+4) | O6: =IF(N6="","",INDEX(Planes!$B$4:$B$6,MATCH(N6,Planes!$A$4:$A$6,0))) | P6: Enviar mensaje 1b | R6: Menú en línea con pedidos a WhatsApp (ola.click) | S6: =HYPERLINK("https://familyburger-col.ola.click/","Ver fuente") -> Ver fuente
A7: 6 | B7: Alta | C7: Garage Burger 66 | D7: Bello | E7: La Madera | F7: Hamburguesas | H7: =IF(G7="","Sin número",IF(LEFT(G7,1)="3","Celular","Fijo")) -> Sin número | I7: =IF(H7="Celular",HYPERLINK("https://wa.me/57"&G7,"Abrir chat"),"") | J7: Cra 53 # 26B-26 | K7: Por contactar | M7: =IF(L7="","",L7+4) | O7: =IF(N7="","",INDEX(Planes!$B$4:$B$6,MATCH(N7,Planes!$A$4:$A$6,0))) | P7: Escribir por el botón de WhatsApp de su menú en línea | R7: Menú en línea con pedidos a WhatsApp (ola.click) | S7: =HYPERLINK("https://garage-burger-66.ola.click/","Ver fuente") -> Ver fuente
A8: 7 | B8: Alta | C8: GUSLAB | D8: Bello | E8: La Mesa | F8: Restaurante | G8: 3332578535 | H8: =IF(G8="","Sin número",IF(LEFT(G8,1)="3","Celular","Fijo")) -> Celular | I8: =IF(H8="Celular",HYPERLINK("https://wa.me/57"&G8,"Abrir chat"),"") -> Abrir chat | J8: Cl 53A # 52-39 | K8: Por contactar | M8: =IF(L8="","",L8+4) | O8: =IF(N8="","",INDEX(Planes!$B$4:$B$6,MATCH(N8,Planes!$A$4:$A$6,0))) | P8: Enviar mensaje 1b | R8: Menú en línea con pedidos a WhatsApp (ola.click) | S8: =HYPERLINK("https://guslab.ola.click/","Ver fuente") -> Ver fuente
A9: 8 | B9: Alta | C9: Los Mandingos | D9: Bello | E9: La Cabaña | F9: Restaurante | H9: =IF(G9="","Sin número",IF(LEFT(G9,1)="3","Celular","Fijo")) -> Sin número | I9: =IF(H9="Celular",HYPERLINK("https://wa.me/57"&G9,"Abrir chat"),"") | K9: Por contactar | M9: =IF(L9="","",L9+4) | O9: =IF(N9="","",INDEX(Planes!$B$4:$B$6,MATCH(N9,Planes!$A$4:$A$6,0))) | P9: Escribir por el botón de WhatsApp de su menú en línea | R9: Menú en línea con pedidos a WhatsApp (ola.click) | S9: =HYPERLINK("https://los-mandingos.ola.click/","Ver fuente") -> Ver fuente
A10: 9 | B10: Alta | C10: Restaurante Cuernavaca | D10: Bello | E10: Centro | F10: Comida mexicana y típica | G10: 3187838904 | H10: =IF(G10="","Sin número",IF(LEFT(G10,1)="3","Celular","Fijo")) -> Celular | I10: =IF(H10="Celular",HYPERLINK("https://wa.me/57"&G10,"Abrir chat"),"") -> Abrir chat | J10: Cra 51 # 51-27 | K10: Por contactar | M10: =IF(L10="","",L10+4) | O10: =IF(N10="","",INDEX(Planes!$B$4:$B$6,MATCH(N10,Planes!$A$4:$A$6,0))) | P10: Enviar mensaje 1b | R10: Menú en línea con pedidos a WhatsApp (ola.click) | S10: =HYPERLINK("https://cuernavaca.ola.click/","Ver fuente") -> Ver fuente
A11: 10 | B11: Alta | C11: Alabama | D11: Medellín | E11: El Poblado | F11: Almuerzos caseros | H11: =IF(G11="","Sin número",IF(LEFT(G11,1)="3","Celular","Fijo")) -> Sin número | I11: =IF(H11="Celular",HYPERLINK("https://wa.me/57"&G11,"Abrir chat"),"") | K11: Por contactar | M11: =IF(L11="","",L11+4) | O11: =IF(N11="","",INDEX(Planes!$B$4:$B$6,MATCH(N11,Planes!$A$4:$A$6,0))) | P11: Escribir por el botón de WhatsApp de su menú en línea | R11: Manda el menú del día por WhatsApp y recibe los pedidos por ahí | S11: =HYPERLINK("https://alabama.soy/almuerzo-casero-medellin/","Ver fuente") -> Ver fuente
A12: 11 | B12: Alta | C12: Arepapas | D12: Medellín | E12: Laureles | F12: Arepería | G12: 3052572323 | H12: =IF(G12="","Sin número",IF(LEFT(G12,1)="3","Celular","Fijo")) -> Celular | I12: =IF(H12="Celular",HYPERLINK("https://wa.me/57"&G12,"Abrir chat"),"") -> Abrir chat | J12: Cl 43 # 76-10 | K12: Por contactar | M12: =IF(L12="","",L12+4) | O12: =IF(N12="","",INDEX(Planes!$B$4:$B$6,MATCH(N12,Planes!$A$4:$A$6,0))) | P12: Enviar mensaje 1b | R12: Menú en línea con pedidos a WhatsApp (ola.click) | S12: =HYPERLINK("https://arepapas.ola.click/","Ver fuente") -> Ver fuente
A13: 12 | B13: Alta | C13: Benditas Papas | D13: Medellín | E13: Buenos Aires | F13: Comida rápida | G13: 3137842015 | H13: =IF(G13="","Sin número",IF(LEFT(G13,1)="3","Celular","Fijo")) -> Celular | I13: =IF(H13="Celular",HYPERLINK("https://wa.me/57"&G13,"Abrir chat"),"") -> Abrir chat | J13: Cl 50 # 27A-87 | K13: Por contactar | M13: =IF(L13="","",L13+4) | O13: =IF(N13="","",INDEX(Planes!$B$4:$B$6,MATCH(N13,Planes!$A$4:$A$6,0))) | P13: Enviar mensaje 1b | R13: Menú en línea con pedidos a WhatsApp (ola.click) | S13: =HYPERLINK("https://benditas-papas.ola.click/","Ver fuente") -> Ver fuente
A14: 13 | B14: Alta | C14: Brosty Combo La Y | D14: Medellín | E14: Buenos Aires | F14: Asadero | G14: 3027017636 | H14: =IF(G14="","Sin número",IF(LEFT(G14,1)="3","Celular","Fijo")) -> Celular | I14: =IF(H14="Celular",HYPERLINK("https://wa.me/57"&G14,"Abrir chat"),"") -> Abrir chat | J14: Cl 49 # 7-10, Barrios de Jesús | K14: Por contactar | M14: =IF(L14="","",L14+4) | O14: =IF(N14="","",INDEX(Planes!$B$4:$B$6,MATCH(N14,Planes!$A$4:$A$6,0))) | P14: Enviar mensaje 1b | R14: Menú en línea con pedidos a WhatsApp (ola.click) | S14: =HYPERLINK("https://brosty-combo-la-y.ola.click/","Ver fuente") -> Ver fuente
A15: 14 | B15: Alta | C15: Bárbaro Cocina Primitiva | D15: Medellín | E15: El Poblado / Laureles | F15: Restaurante con domicilios | G15: 3176762292 | H15: =IF(G15="","Sin número",IF(LEFT(G15,1)="3","Celular","Fijo")) -> Celular | I15: =IF(H15="Celular",HYPERLINK("https://wa.me/57"&G15,"Abrir chat"),"") -> Abrir chat | K15: Por contactar | M15: =IF(L15="","",L15+4) | O15: =IF(N15="","",INDEX(Planes!$B$4:$B$6,MATCH(N15,Planes!$A$4:$A$6,0))) | P15: Enviar mensaje 1b | R15: Domicilios por WhatsApp (guía de 2020); Laureles: 3182822160 | S15: =HYPERLINK("https://medellinguru.com/?p=24707","Ver fuente") -> Ver fuente
A16: 15 | B16: Alta | C16: Casa del Arroz | D16: Medellín | E16: Belén | F16: Arroces | G16: 3019075390 | H16: =IF(G16="","Sin número",IF(LEFT(G16,1)="3","Celular","Fijo")) -> Celular | I16: =IF(H16="Celular",HYPERLINK("https://wa.me/57"&G16,"Abrir chat"),"") -> Abrir chat | J16: Cl 30A # 82A-26 | K16: Por contactar | M16: =IF(L16="","",L16+4) | O16: =IF(N16="","",INDEX(Planes!$B$4:$B$6,MATCH(N16,Planes!$A$4:$A$6,0))) | P16: Enviar mensaje 1b | R16: Menú en línea con pedidos a WhatsApp (ola.click) | S16: =HYPERLINK("https://casa-del-arroz.ola.click/","Ver fuente") -> Ver fuente
A17: 16 | B17: Alta | C17: Comidas Rápidas de la Villa | D17: Medellín | E17: Belén | F17: Comida rápida | G17: 3015745474 | H17: =IF(G17="","Sin número",IF(LEFT(G17,1)="3","Celular","Fijo")) -> Celular | I17: =IF(H17="Celular",HYPERLINK("https://wa.me/57"&G17,"Abrir chat"),"") -> Abrir chat | J17: Cra 81 # 32C-2 | K17: Por contactar | M17: =IF(L17="","",L17+4) | O17: =IF(N17="","",INDEX(Planes!$B$4:$B$6,MATCH(N17,Planes!$A$4:$A$6,0))) | P17: Enviar mensaje 1b | R17: Menú en línea con pedidos a WhatsApp (ola.click) | S17: =HYPERLINK("https://comidas-rapidas-juan.ola.click/","Ver fuente") -> Ver fuente
A18: 17 | B18: Alta | C18: Comidas Rápidas DTia | D18: Medellín | E18: Aranjuez | F18: Comida rápida | G18: 3002025959 | H18: =IF(G18="","Sin número",IF(LEFT(G18,1)="3","Celular","Fijo")) -> Celular | I18: =IF(H18="Celular",HYPERLINK("https://wa.me/57"&G18,"Abrir chat"),"") -> Abrir chat | J18: Cra 53 # 94-71 | K18: Por contactar | M18: =IF(L18="","",L18+4) | O18: =IF(N18="","",INDEX(Planes!$B$4:$B$6,MATCH(N18,Planes!$A$4:$A$6,0))) | P18: Enviar mensaje 1b | R18: Menú en línea con pedidos a WhatsApp (ola.click) | S18: =HYPERLINK("https://comidasrapidas-dtia.ola.click/","Ver fuente") -> Ver fuente
A19: 18 | B19: Alta | C19: Correo Carne y Vino | D19: Medellín | E19: Laureles | F19: Restaurante con domicilios | G19: 3107693578 | H19: =IF(G19="","Sin número",IF(LEFT(G19,1)="3","Celular","Fijo")) -> Celular | I19: =IF(H19="Celular",HYPERLINK("https://wa.me/57"&G19,"Abrir chat"),"") -> Abrir chat | K19: Por contactar | M19: =IF(L19="","",L19+4) | O19: =IF(N19="","",INDEX(Planes!$B$4:$B$6,MATCH(N19,Planes!$A$4:$A$6,0))) | P19: Enviar mensaje 1b | R19: Domicilios por WhatsApp (guía de 2020) | S19: =HYPERLINK("https://medellinguru.com/?p=24707","Ver fuente") -> Ver fuente
A20: 19 | B20: Alta | C20: CR Delicias del Barrio | D20: Medellín | E20: Aranjuez | F20: Comida casera | G20: 3135566907 | H20: =IF(G20="","Sin número",IF(LEFT(G20,1)="3","Celular","Fijo")) -> Celular | I20: =IF(H20="Celular",HYPERLINK("https://wa.me/57"&G20,"Abrir chat"),"") -> Abrir chat | J20: Cl 85 # 57A-99 | K20: Por contactar | M20: =IF(L20="","",L20+4) | O20: =IF(N20="","",INDEX(Planes!$B$4:$B$6,MATCH(N20,Planes!$A$4:$A$6,0))) | P20: Enviar mensaje 1b | R20: Menú en línea con pedidos a WhatsApp (ola.click) | S20: =HYPERLINK("https://cr-delicias-del-barrio.ola.click/","Ver fuente") -> Ver fuente
A21: 20 | B21: Alta | C21: Criollas House | D21: Medellín | F21: Comida rápida | G21: 3246020193 | H21: =IF(G21="","Sin número",IF(LEFT(G21,1)="3","Celular","Fijo")) -> Celular | I21: =IF(H21="Celular",HYPERLINK("https://wa.me/57"&G21,"Abrir chat"),"") -> Abrir chat | J21: Cl 91 # 50C-43 | K21: Por contactar | M21: =IF(L21="","",L21+4) | O21: =IF(N21="","",INDEX(Planes!$B$4:$B$6,MATCH(N21,Planes!$A$4:$A$6,0))) | P21: Enviar mensaje 1b | R21: Menú en línea con pedidos a WhatsApp (ola.click) | S21: =HYPERLINK("https://criollashouse.ola.click/","Ver fuente") -> Ver fuente
A22: 21 | B22: Alta | C22: Deliperros y Parrilla | D22: Medellín | F22: Comida rápida | G22: 3206544335 | H22: =IF(G22="","Sin número",IF(LEFT(G22,1)="3","Celular","Fijo")) -> Celular | I22: =IF(H22="Celular",HYPERLINK("https://wa.me/57"&G22,"Abrir chat"),"") -> Abrir chat | J22: Cl 60 # 75-40 | K22: Por contactar | M22: =IF(L22="","",L22+4) | O22: =IF(N22="","",INDEX(Planes!$B$4:$B$6,MATCH(N22,Planes!$A$4:$A$6,0))) | P22: Enviar mensaje 1b | R22: Menú en línea con pedidos a WhatsApp (ola.click) | S22: =HYPERLINK("https://deliperrosyparrilla.ola.click/","Ver fuente") -> Ver fuente
A23: 22 | B23: Alta | C23: Delirio Exquisito | D23: Medellín | E23: El Poblado / Laureles | F23: Restaurante con domicilios | G23: 3113663840 | H23: =IF(G23="","Sin número",IF(LEFT(G23,1)="3","Celular","Fijo")) -> Celular | I23: =IF(H23="Celular",HYPERLINK("https://wa.me/57"&G23,"Abrir chat"),"") -> Abrir chat | K23: Por contactar | M23: =IF(L23="","",L23+4) | O23: =IF(N23="","",INDEX(Planes!$B$4:$B$6,MATCH(N23,Planes!$A$4:$A$6,0))) | P23: Enviar mensaje 1b | Q23: Otro número: 3505671075 | R23: Domicilios por WhatsApp (guía de 2020) | S23: =HYPERLINK("https://medellinguru.com/?p=24612","Ver fuente") -> Ver fuente
A24: 23 | B24: Alta | C24: Due Amici Pizzería | D24: Medellín | E24: Laureles | F24: Pizzería | G24: 3107693578 | H24: =IF(G24="","Sin número",IF(LEFT(G24,1)="3","Celular","Fijo")) -> Celular | I24: =IF(H24="Celular",HYPERLINK("https://wa.me/57"&G24,"Abrir chat"),"") -> Abrir chat | K24: Por contactar | M24: =IF(L24="","",L24+4) | O24: =IF(N24="","",INDEX(Planes!$B$4:$B$6,MATCH(N24,Planes!$A$4:$A$6,0))) | P24: Enviar mensaje 1b | R24: Domicilios por WhatsApp (guía de 2020); el mismo número aparece para Correo Carne y Vino | S24: =HYPERLINK("https://medellinguru.com/laureles-with-domicilio/","Ver fuente") -> Ver fuente
A25: 24 | B25: Alta | C25: El Puto Taco | D25: Medellín | E25: Laureles | F25: Comida mexicana | H25: =IF(G25="","Sin número",IF(LEFT(G25,1)="3","Celular","Fijo")) -> Sin número | I25: =IF(H25="Celular",HYPERLINK("https://wa.me/57"&G25,"Abrir chat"),"") | J25: Tv 5A # 45-337 | K25: Por contactar | M25: =IF(L25="","",L25+4) | O25: =IF(N25="","",INDEX(Planes!$B$4:$B$6,MATCH(N25,Planes!$A$4:$A$6,0))) | P25: Escribir por el botón de WhatsApp de su menú en línea | R25: Menú en línea con pedidos a WhatsApp (ola.click) | S25: =HYPERLINK("https://elputotaco2.ola.click/products","Ver fuente") -> Ver fuente
A26: 25 | B26: Alta | C26: Escudero's BBQ | D26: Medellín | E26: Guayabal | F26: Parrilla | G26: 3017478418 | H26: =IF(G26="","Sin número",IF(LEFT(G26,1)="3","Celular","Fijo")) -> Celular | I26: =IF(H26="Celular",HYPERLINK("https://wa.me/57"&G26,"Abrir chat"),"") -> Abrir chat | J26: Cl 1 # 53-62 | K26: Por contactar | M26: =IF(L26="","",L26+4) | O26: =IF(N26="","",INDEX(Planes!$B$4:$B$6,MATCH(N26,Planes!$A$4:$A$6,0))) | P26: Enviar mensaje 1b | R26: Menú en línea con pedidos a WhatsApp (ola.click) | S26: =HYPERLINK("https://escuderosbbq.ola.click/","Ver fuente") -> Ver fuente
A27: 26 | B27: Alta | C27: Freedog Oviedo | D27: Medellín | E27: El Poblado | F27: Comida rápida | H27: =IF(G27="","Sin número",IF(LEFT(G27,1)="3","Celular","Fijo")) -> Sin número | I27: =IF(H27="Celular",HYPERLINK("https://wa.me/57"&G27,"Abrir chat"),"") | J27: Cra 43A # 6 Sur-15 | K27: Por contactar | M27: =IF(L27="","",L27+4) | O27: =IF(N27="","",INDEX(Planes!$B$4:$B$6,MATCH(N27,Planes!$A$4:$A$6,0))) | P27: Escribir por el botón de WhatsApp de su menú en línea | R27: Menú en línea con pedidos a WhatsApp (ola.click) | S27: =HYPERLINK("https://freedogcolombia.ola.click/","Ver fuente") -> Ver fuente
A28: 27 | B28: Alta | C28: Kuelap | D28: Medellín | E28: El Poblado | F28: Restaurante peruano | G28: 3164312245 | H28: =IF(G28="","Sin número",IF(LEFT(G28,1)="3","Celular","Fijo")) -> Celular | I28: =IF(H28="Celular",HYPERLINK("https://wa.me/57"&G28,"Abrir chat"),"") -> Abrir chat | J28: Cl 3 Sur # 43A-40 | K28: Por contactar | M28: =IF(L28="","",L28+4) | O28: =IF(N28="","",INDEX(Planes!$B$4:$B$6,MATCH(N28,Planes!$A$4:$A$6,0))) | P28: Enviar mensaje 1b | R28: Domicilios por WhatsApp (guía de 2020) | S28: =HYPERLINK("https://medellinguru.com/kuelap/","Ver fuente") -> Ver fuente
A29: 28 | B29: Alta | C29: La Chimichanga | D29: Medellín | E29: Belén | F29: Comida mexicana | G29: 3015312571 | H29: =IF(G29="","Sin número",IF(LEFT(G29,1)="3","Celular","Fijo")) -> Celular | I29: =IF(H29="Celular",HYPERLINK("https://wa.me/57"&G29,"Abrir chat"),"") -> Abrir chat | J29: Cl 3C # 77A-14 | K29: Por contactar | M29: =IF(L29="","",L29+4) | O29: =IF(N29="","",INDEX(Planes!$B$4:$B$6,MATCH(N29,Planes!$A$4:$A$6,0))) | P29: Enviar mensaje 1b | R29: Menú en línea con pedidos a WhatsApp (ola.click) | S29: =HYPERLINK("https://lachimichanga.ola.click/","Ver fuente") -> Ver fuente
A30: 29 | B30: Alta | C30: La Chorizería | D30: Medellín | E30: Laureles | F30: Comida rápida | G30: 3112073817 | H30: =IF(G30="","Sin número",IF(LEFT(G30,1)="3","Celular","Fijo")) -> Celular | I30: =IF(H30="Celular",HYPERLINK("https://wa.me/57"&G30,"Abrir chat"),"") -> Abrir chat | J30: Cl 35 # 80A-70 | K30: Por contactar | M30: =IF(L30="","",L30+4) | O30: =IF(N30="","",INDEX(Planes!$B$4:$B$6,MATCH(N30,Planes!$A$4:$A$6,0))) | P30: Enviar mensaje 1b | R30: Menú en línea con pedidos a WhatsApp (ola.click) | S30: =HYPERLINK("https://la-choriceria.ola.click/","Ver fuente") -> Ver fuente
A31: 30 | B31: Alta | C31: La Eterna | D31: Medellín | E31: La Candelaria | F31: Restaurante | G31: 3107364695 | H31: =IF(G31="","Sin número",IF(LEFT(G31,1)="3","Celular","Fijo")) -> Celular | I31: =IF(H31="Celular",HYPERLINK("https://wa.me/57"&G31,"Abrir chat"),"") -> Abrir chat | J31: Cra 50D # 66-39 | K31: Por contactar | M31: =IF(L31="","",L31+4) | O31: =IF(N31="","",INDEX(Planes!$B$4:$B$6,MATCH(N31,Planes!$A$4:$A$6,0))) | P31: Enviar mensaje 1b | R31: Menú en línea con pedidos a WhatsApp (ola.click) | S31: =HYPERLINK("https://la-eterna-2.ola.click/","Ver fuente") -> Ver fuente
A32: 31 | B32: Alta | C32: La Locura de Celia | D32: Medellín | E32: Laureles | F32: Asadero | H32: =IF(G32="","Sin número",IF(LEFT(G32,1)="3","Celular","Fijo")) -> Sin número | I32: =IF(H32="Celular",HYPERLINK("https://wa.me/57"&G32,"Abrir chat"),"") | J32: Cra 80A # 35-13 | K32: Por contactar | M32: =IF(L32="","",L32+4) | O32: =IF(N32="","",INDEX(Planes!$B$4:$B$6,MATCH(N32,Planes!$A$4:$A$6,0))) | P32: Escribir por el botón de WhatsApp de su menú en línea | R32: Menú en línea con pedidos a WhatsApp (ola.click) | S32: =HYPERLINK("https://la-locura-de-celia-asado-restaurante.ola.click/","Ver fuente") -> Ver fuente
A33: 32 | B33: Alta | C33: La Sazón de ALDE | D33: Medellín | E33: Laureles | F33: Comida casera | G33: 3013894096 | H33: =IF(G33="","Sin número",IF(LEFT(G33,1)="3","Celular","Fijo")) -> Celular | I33: =IF(H33="Celular",HYPERLINK("https://wa.me/57"&G33,"Abrir chat"),"") -> Abrir chat | J33: Av Bolivariana # 42B-16 | K33: Por contactar | M33: =IF(L33="","",L33+4) | O33: =IF(N33="","",INDEX(Planes!$B$4:$B$6,MATCH(N33,Planes!$A$4:$A$6,0))) | P33: Enviar mensaje 1b | R33: Menú en línea con pedidos a WhatsApp (ola.click) | S33: =HYPERLINK("https://lasazondealde.ola.click/","Ver fuente") -> Ver fuente
A34: 33 | B34: Alta | C34: Lo Exquisito del Mar | D34: Medellín | E34: Laureles | F34: Comida de mar | G34: 3194189670 | H34: =IF(G34="","Sin número",IF(LEFT(G34,1)="3","Celular","Fijo")) -> Celular | I34: =IF(H34="Celular",HYPERLINK("https://wa.me/57"&G34,"Abrir chat"),"") -> Abrir chat | K34: Por contactar | M34: =IF(L34="","",L34+4) | O34: =IF(N34="","",INDEX(Planes!$B$4:$B$6,MATCH(N34,Planes!$A$4:$A$6,0))) | P34: Enviar mensaje 1b | R34: Domicilios por WhatsApp (guía de 2020; también 3023301037) | S34: =HYPERLINK("https://medellinguru.com/laureles-with-domicilio/","Ver fuente") -> Ver fuente
A35: 34 | B35: Alta | C35: Los Costeñitos Exprés | D35: Medellín | E35: Laureles | F35: Comida costeña | G35: 3217791979 | H35: =IF(G35="","Sin número",IF(LEFT(G35,1)="3","Celular","Fijo")) -> Celular | I35: =IF(H35="Celular",HYPERLINK("https://wa.me/57"&G35,"Abrir chat"),"") -> Abrir chat | J35: Cra 74 # 53-162 | K35: Por contactar | M35: =IF(L35="","",L35+4) | O35: =IF(N35="","",INDEX(Planes!$B$4:$B$6,MATCH(N35,Planes!$A$4:$A$6,0))) | P35: Enviar mensaje 1b | R35: Menú en línea con pedidos a WhatsApp (ola.click) | S35: =HYPERLINK("https://los-costenitos-expres.ola.click/","Ver fuente") -> Ver fuente
A36: 35 | B36: Alta | C36: Lupita Cocina Peruana | D36: Medellín | E36: Centro | F36: Restaurante peruano | G36: 3177178229 | H36: =IF(G36="","Sin número",IF(LEFT(G36,1)="3","Celular","Fijo")) -> Celular | I36: =IF(H36="Celular",HYPERLINK("https://wa.me/57"&G36,"Abrir chat"),"") -> Abrir chat | J36: Cra 43 # 52-101 | K36: Por contactar | M36: =IF(L36="","",L36+4) | O36: =IF(N36="","",INDEX(Planes!$B$4:$B$6,MATCH(N36,Planes!$A$4:$A$6,0))) | P36: Enviar mensaje 1b | R36: Menú en línea con pedidos a WhatsApp (ola.click) | S36: =HYPERLINK("https://lupita-col.ola.click/","Ver fuente") -> Ver fuente
A37: 36 | B37: Alta | C37: Mr. Will Restaurante | D37: Medellín | E37: Laureles | F37: Restaurante | G37: 3187587404 | H37: =IF(G37="","Sin número",IF(LEFT(G37,1)="3","Celular","Fijo")) -> Celular | I37: =IF(H37="Celular",HYPERLINK("https://wa.me/57"&G37,"Abrir chat"),"") -> Abrir chat | J37: Cra 69A # 44B-115 | K37: Por contactar | M37: =IF(L37="","",L37+4) | O37: =IF(N37="","",INDEX(Planes!$B$4:$B$6,MATCH(N37,Planes!$A$4:$A$6,0))) | P37: Enviar mensaje 1b | R37: Menú en línea con pedidos a WhatsApp (ola.click) | S37: =HYPERLINK("https://restaurantemrwill.ola.click/","Ver fuente") -> Ver fuente
A38: 37 | B38: Alta | C38: Muzarella's Pizza | D38: Medellín | E38: Robledo | F38: Pizzería | H38: =IF(G38="","Sin número",IF(LEFT(G38,1)="3","Celular","Fijo")) -> Sin número | I38: =IF(H38="Celular",HYPERLINK("https://wa.me/57"&G38,"Abrir chat"),"") | J38: Villa Flora | K38: Por contactar | M38: =IF(L38="","",L38+4) | O38: =IF(N38="","",INDEX(Planes!$B$4:$B$6,MATCH(N38,Planes!$A$4:$A$6,0))) | P38: Escribir por el botón de WhatsApp de su menú en línea | R38: Menú en línea con pedidos a WhatsApp (ola.click) | S38: =HYPERLINK("https://muzarellas-pizza.ola.click/","Ver fuente") -> Ver fuente
A39: 38 | B39: Alta | C39: Parrilla Bar Nogales Barbecue | D39: Medellín | E39: Belén | F39: Parrilla | G39: 3103758138 | H39: =IF(G39="","Sin número",IF(LEFT(G39,1)="3","Celular","Fijo")) -> Celular | I39: =IF(H39="Celular",HYPERLINK("https://wa.me/57"&G39,"Abrir chat"),"") -> Abrir chat | J39: Cl 32EE # 78-109 | K39: Por contactar | M39: =IF(L39="","",L39+4) | O39: =IF(N39="","",INDEX(Planes!$B$4:$B$6,MATCH(N39,Planes!$A$4:$A$6,0))) | P39: Enviar mensaje 1b | R39: Menú en línea con pedidos a WhatsApp (ola.click) | S39: =HYPERLINK("https://parrilla-nogales-barbecue.ola.click/","Ver fuente") -> Ver fuente
A40: 39 | B40: Alta | C40: Parrillas Caracas | D40: Medellín | E40: Laureles | F40: Parrilla | H40: =IF(G40="","Sin número",IF(LEFT(G40,1)="3","Celular","Fijo")) -> Sin número | I40: =IF(H40="Celular",HYPERLINK("https://wa.me/57"&G40,"Abrir chat"),"") | J40: Cra 78 # 45A-04 | K40: Por contactar | M40: =IF(L40="","",L40+4) | O40: =IF(N40="","",INDEX(Planes!$B$4:$B$6,MATCH(N40,Planes!$A$4:$A$6,0))) | P40: Escribir por el botón de WhatsApp de su menú en línea | R40: Menú en línea con pedidos a WhatsApp (ola.click) | S40: =HYPERLINK("https://parrillas-caracas.ola.click/","Ver fuente") -> Ver fuente
A41: 40 | B41: Alta | C41: Pigasus | D41: Medellín | E41: Belén / Laureles | F41: Hamburguesas | G41: 3162348112 | H41: =IF(G41="","Sin número",IF(LEFT(G41,1)="3","Celular","Fijo")) -> Celular | I41: =IF(H41="Celular",HYPERLINK("https://wa.me/57"&G41,"Abrir chat"),"") -> Abrir chat | K41: Por contactar | M41: =IF(L41="","",L41+4) | O41: =IF(N41="","",INDEX(Planes!$B$4:$B$6,MATCH(N41,Planes!$A$4:$A$6,0))) | P41: Enviar mensaje 1b | R41: Domicilios por WhatsApp (guía) | S41: =HYPERLINK("https://medellinguru.com/pigasus/","Ver fuente") -> Ver fuente
A42: 41 | B42: Alta | C42: PPLP Pizzas, Pastas y Lasaña | D42: Medellín | F42: Pizzería | H42: =IF(G42="","Sin número",IF(LEFT(G42,1)="3","Celular","Fijo")) -> Sin número | I42: =IF(H42="Celular",HYPERLINK("https://wa.me/57"&G42,"Abrir chat"),"") | K42: Por contactar | M42: =IF(L42="","",L42+4) | O42: =IF(N42="","",INDEX(Planes!$B$4:$B$6,MATCH(N42,Planes!$A$4:$A$6,0))) | P42: Escribir por el botón de WhatsApp de su menú en línea | R42: Menú en línea con pedidos a WhatsApp (ola.click) | S42: =HYPERLINK("https://pplp.ola.click/","Ver fuente") -> Ver fuente
A43: 42 | B43: Alta | C43: Puro Coco | D43: Medellín | E43: Laureles | F43: Comida de mar | G43: 3002225032 | H43: =IF(G43="","Sin número",IF(LEFT(G43,1)="3","Celular","Fijo")) -> Celular | I43: =IF(H43="Celular",HYPERLINK("https://wa.me/57"&G43,"Abrir chat"),"") -> Abrir chat | J43: Cl 44A # 77-64 | K43: Por contactar | M43: =IF(L43="","",L43+4) | O43: =IF(N43="","",INDEX(Planes!$B$4:$B$6,MATCH(N43,Planes!$A$4:$A$6,0))) | P43: Enviar mensaje 1b | R43: Menú en línea con pedidos a WhatsApp (ola.click) | S43: =HYPERLINK("https://puro-coco.ola.click/","Ver fuente") -> Ver fuente
A44: 43 | B44: Alta | C44: Ricomilones Medellín | D44: Medellín | E44: Centro | F44: Comida rápida | G44: 3212549016 | H44: =IF(G44="","Sin número",IF(LEFT(G44,1)="3","Celular","Fijo")) -> Celular | I44: =IF(H44="Celular",HYPERLINK("https://wa.me/57"&G44,"Abrir chat"),"") -> Abrir chat | J44: Cra 50 # 52-2 | K44: Por contactar | M44: =IF(L44="","",L44+4) | O44: =IF(N44="","",INDEX(Planes!$B$4:$B$6,MATCH(N44,Planes!$A$4:$A$6,0))) | P44: Enviar mensaje 1b | R44: Menú en línea con pedidos a WhatsApp (ola.click) | S44: =HYPERLINK("https://ricomilones.ola.click/","Ver fuente") -> Ver fuente
A45: 44 | B45: Alta | C45: Rocoto | D45: Medellín | E45: El Poblado | F45: Restaurante peruano | G45: 3117841355 | H45: =IF(G45="","Sin número",IF(LEFT(G45,1)="3","Celular","Fijo")) -> Celular | I45: =IF(H45="Celular",HYPERLINK("https://wa.me/57"&G45,"Abrir chat"),"") -> Abrir chat | J45: Cra 33 # 8A-15 | K45: Por contactar | M45: =IF(L45="","",L45+4) | O45: =IF(N45="","",INDEX(Planes!$B$4:$B$6,MATCH(N45,Planes!$A$4:$A$6,0))) | P45: Enviar mensaje 1b | R45: Domicilios por WhatsApp (guía de 2020) | S45: =HYPERLINK("https://medellinguru.com/rocoto/","Ver fuente") -> Ver fuente
A46: 45 | B46: Alta | C46: Romero Cocina Artesanal | D46: Medellín | E46: Laureles | F46: Restaurante italiano | G46: 3154717699 | H46: =IF(G46="","Sin número",IF(LEFT(G46,1)="3","Celular","Fijo")) -> Celular | I46: =IF(H46="Celular",HYPERLINK("https://wa.me/57"&G46,"Abrir chat"),"") -> Abrir chat | K46: Por contactar | M46: =IF(L46="","",L46+4) | O46: =IF(N46="","",INDEX(Planes!$B$4:$B$6,MATCH(N46,Planes!$A$4:$A$6,0))) | P46: Enviar mensaje 1b | R46: Domicilios por WhatsApp (guía de 2020) | S46: =HYPERLINK("https://medellinguru.com/laureles-with-domicilio/","Ver fuente") -> Ver fuente
A47: 46 | B47: Alta | C47: The Garden | D47: Medellín | E47: El Poblado | F47: Restaurante | H47: =IF(G47="","Sin número",IF(LEFT(G47,1)="3","Celular","Fijo")) -> Sin número | I47: =IF(H47="Celular",HYPERLINK("https://wa.me/57"&G47,"Abrir chat"),"") | J47: Cra 32D # 9-17 | K47: Por contactar | M47: =IF(L47="","",L47+4) | O47: =IF(N47="","",INDEX(Planes!$B$4:$B$6,MATCH(N47,Planes!$A$4:$A$6,0))) | P47: Escribir por el botón de WhatsApp de su menú en línea | R47: Menú en línea con pedidos a WhatsApp (ola.click) | S47: =HYPERLINK("https://thegarden.ola.click/","Ver fuente") -> Ver fuente
A48: 47 | B48: Alta | C48: Voraz Restaurante | D48: Medellín | E48: Laureles | F48: Parrilla | G48: 3162211687 | H48: =IF(G48="","Sin número",IF(LEFT(G48,1)="3","Celular","Fijo")) -> Celular | I48: =IF(H48="Celular",HYPERLINK("https://wa.me/57"&G48,"Abrir chat"),"") -> Abrir chat | K48: Por contactar | M48: =IF(L48="","",L48+4) | O48: =IF(N48="","",INDEX(Planes!$B$4:$B$6,MATCH(N48,Planes!$A$4:$A$6,0))) | P48: Enviar mensaje 1b | R48: Domicilios por WhatsApp (guía de 2020) | S48: =HYPERLINK("https://medellinguru.com/laureles-with-domicilio/","Ver fuente") -> Ver fuente
A49: 48 | B49: Alta | C49: Yony Perros | D49: Medellín | E49: Robledo | F49: Comida rápida | G49: 3007541651 | H49: =IF(G49="","Sin número",IF(LEFT(G49,1)="3","Celular","Fijo")) -> Celular | I49: =IF(H49="Celular",HYPERLINK("https://wa.me/57"&G49,"Abrir chat"),"") -> Abrir chat | J49: Cl 73 # 76A-354, Pilarica | K49: Por contactar | M49: =IF(L49="","",L49+4) | O49: =IF(N49="","",INDEX(Planes!$B$4:$B$6,MATCH(N49,Planes!$A$4:$A$6,0))) | P49: Enviar mensaje 1b | R49: Menú en línea con pedidos a WhatsApp (ola.click) | S49: =HYPERLINK("https://yony-perros.ola.click/","Ver fuente") -> Ver fuente
A50: 49 | B50: Media | C50: Alimentos Rápido y Sabroso SAS | D50: Bello | F50: Comida rápida | G50: 3502977864 | H50: =IF(G50="","Sin número",IF(LEFT(G50,1)="3","Celular","Fijo")) -> Celular | I50: =IF(H50="Celular",HYPERLINK("https://wa.me/57"&G50,"Abrir chat"),"") -> Abrir chat | J50: Cl 20F # 44-40 | K50: Por contactar | M50: =IF(L50="","",L50+4) | O50: =IF(N50="","",INDEX(Planes!$B$4:$B$6,MATCH(N50,Planes!$A$4:$A$6,0))) | P50: Enviar mensaje 1 | R50: Sin confirmar | S50: =HYPERLINK("https://www.informacolombia.com/directorio-empresas/informacion-empresa/alimentos-rapido-sabroso-sas","Ver fuente") -> Ver fuente
A51: 50 | B51: Media | C51: Collazos Sabores y Tradición SAS | D51: Bello | F51: Restaurante | G51: 3106867462 | H51: =IF(G51="","Sin número",IF(LEFT(G51,1)="3","Celular","Fijo")) -> Celular | I51: =IF(H51="Celular",HYPERLINK("https://wa.me/57"&G51,"Abrir chat"),"") -> Abrir chat | J51: Cl 52 # 47-20 | K51: Por contactar | M51: =IF(L51="","",L51+4) | O51: =IF(N51="","",INDEX(Planes!$B$4:$B$6,MATCH(N51,Planes!$A$4:$A$6,0))) | P51: Enviar mensaje 1 | R51: Sin confirmar | S51: =HYPERLINK("https://www.informacolombia.com/directorio-empresas/informacion-empresa/collazos-sabores-tradicion-sas","Ver fuente") -> Ver fuente
A52: 51 | B52: Media | C52: Gourmet & Parrilla SAS | D52: Bello | F52: Parrilla | G52: 3106909696 | H52: =IF(G52="","Sin número",IF(LEFT(G52,1)="3","Celular","Fijo")) -> Celular | I52: =IF(H52="Celular",HYPERLINK("https://wa.me/57"&G52,"Abrir chat"),"") -> Abrir chat | J52: Cra 50 # 38A-185 | K52: Por contactar | M52: =IF(L52="","",L52+4) | O52: =IF(N52="","",INDEX(Planes!$B$4:$B$6,MATCH(N52,Planes!$A$4:$A$6,0))) | P52: Enviar mensaje 1 | R52: Sin confirmar | S52: =HYPERLINK("https://directorio-empresas.einforma.co/informacion-empresa/gourmet-parrilla-sas","Ver fuente") -> Ver fuente
A53: 52 | B53: Media | C53: Inversiones Pavesave SAS | D53: Bello | F53: Restaurante (expendio a la mesa) | G53: 3116228250 | H53: =IF(G53="","Sin número",IF(LEFT(G53,1)="3","Celular","Fijo")) -> Celular | I53: =IF(H53="Celular",HYPERLINK("https://wa.me/57"&G53,"Abrir chat"),"") -> Abrir chat | K53: Por contactar | M53: =IF(L53="","",L53+4) | O53: =IF(N53="","",INDEX(Planes!$B$4:$B$6,MATCH(N53,Planes!$A$4:$A$6,0))) | P53: Enviar mensaje 1 | R53: Sin confirmar | S53: =HYPERLINK("https://www.informacolombia.com/directorio-empresas/actividad/5611_EXPENDIO-A-LA-MESA-DE-COMIDAS-PREPARADAS/departamento_antioquia?qPg=18","Ver fuente") -> Ver fuente
A54: 53 | B54: Media | C54: Inversiones PPMZ SAS | D54: Bello | F54: Restaurante (expendio a la mesa) | G54: 3106029755 | H54: =IF(G54="","Sin número",IF(LEFT(G54,1)="3","Celular","Fijo")) -> Celular | I54: =IF(H54="Celular",HYPERLINK("https://wa.me/57"&G54,"Abrir chat"),"") -> Abrir chat | K54: Por contactar | M54: =IF(L54="","",L54+4) | O54: =IF(N54="","",INDEX(Planes!$B$4:$B$6,MATCH(N54,Planes!$A$4:$A$6,0))) | P54: Enviar mensaje 1 | R54: Sin confirmar | S54: =HYPERLINK("https://www.informacolombia.com/directorio-empresas/actividad/5611_EXPENDIO-A-LA-MESA-DE-COMIDAS-PREPARADAS/departamento_antioquia?qPg=18","Ver fuente") -> Ver fuente
A55: 54 | B55: Media | C55: Que Alitas SAS | D55: Bello | F55: Comida rápida | G55: 3192808612 | H55: =IF(G55="","Sin número",IF(LEFT(G55,1)="3","Celular","Fijo")) -> Celular | I55: =IF(H55="Celular",HYPERLINK("https://wa.me/57"&G55,"Abrir chat"),"") -> Abrir chat | J55: Dg 55 # 43-150 | K55: Por contactar | M55: =IF(L55="","",L55+4) | O55: =IF(N55="","",INDEX(Planes!$B$4:$B$6,MATCH(N55,Planes!$A$4:$A$6,0))) | P55: Enviar mensaje 1 | R55: Sin confirmar | S55: =HYPERLINK("https://www.informacolombia.com/directorio-empresas/informacion-empresa/que-alitas-sas","Ver fuente") -> Ver fuente
A56: 55 | B56: Media | C56: San Pío Food SAS | D56: Bello | F56: Comidas | G56: 3103708332 | H56: =IF(G56="","Sin número",IF(LEFT(G56,1)="3","Celular","Fijo")) -> Celular | I56: =IF(H56="Celular",HYPERLINK("https://wa.me/57"&G56,"Abrir chat"),"") -> Abrir chat | J56: Cl 24A # 55-32 | K56: Por contactar | M56: =IF(L56="","",L56+4) | O56: =IF(N56="","",INDEX(Planes!$B$4:$B$6,MATCH(N56,Planes!$A$4:$A$6,0))) | P56: Enviar mensaje 1 | R56: Sin confirmar | S56: =HYPERLINK("https://www.informacolombia.com/directorio-empresas/informacion-empresa/san-pio-food-sas","Ver fuente") -> Ver fuente
A57: 56 | B57: Media | C57: Vikingo Pollo | D57: Bello | F57: Asadero | G57: 3116282314 | H57: =IF(G57="","Sin número",IF(LEFT(G57,1)="3","Celular","Fijo")) -> Celular | I57: =IF(H57="Celular",HYPERLINK("https://wa.me/57"&G57,"Abrir chat"),"") -> Abrir chat | K57: Por contactar | M57: =IF(L57="","",L57+4) | O57: =IF(N57="","",INDEX(Planes!$B$4:$B$6,MATCH(N57,Planes!$A$4:$A$6,0))) | P57: Enviar mensaje 1 | R57: Sin confirmar | S57: =HYPERLINK("https://www.informacolombia.com/directorio-empresas/actividad/560_ACTIVIDADES-DE-SERVICIOS-DE-COMIDAS-Y-BEBIDAS/localidad_bello?qPg=2","Ver fuente") -> Ver fuente
A58: 57 | B58: Media | C58: Ama Restaurante Vegano | D58: Medellín | E58: El Poblado | F58: Restaurante vegano | G58: 3042622923 | H58: =IF(G58="","Sin número",IF(LEFT(G58,1)="3","Celular","Fijo")) -> Celular | I58: =IF(H58="Celular",HYPERLINK("https://wa.me/57"&G58,"Abrir chat"),"") -> Abrir chat | J58: Cl 12 # 43B-2 | K58: Por contactar | M58: =IF(L58="","",L58+4) | O58: =IF(N58="","",INDEX(Planes!$B$4:$B$6,MATCH(N58,Planes!$A$4:$A$6,0))) | P58: Enviar mensaje 1b | R58: Menú en línea con pedidos a WhatsApp (ola.click) | S58: =HYPERLINK("https://ama-restaurante-y-mercado-vegano.ola.click/","Ver fuente") -> Ver fuente
A59: 58 | B59: Media | C59: Arepas Las Chachas SAS | D59: Medellín | F59: Arepería | G59: 3197098156 | H59: =IF(G59="","Sin número",IF(LEFT(G59,1)="3","Celular","Fijo")) -> Celular | I59: =IF(H59="Celular",HYPERLINK("https://wa.me/57"&G59,"Abrir chat"),"") -> Abrir chat | J59: Cra 82A # 30-51 | K59: Por contactar | M59: =IF(L59="","",L59+4) | O59: =IF(N59="","",INDEX(Planes!$B$4:$B$6,MATCH(N59,Planes!$A$4:$A$6,0))) | P59: Enviar mensaje 1 | R59: Sin confirmar | S59: =HYPERLINK("https://directorio-empresas.einforma.co/informacion-empresa/arepas-chachas-sas","Ver fuente") -> Ver fuente
A60: 59 | B60: Media | C60: Asados y Típicos al Carbón SAS | D60: Medellín | E60: Centro | F60: Asados | G60: 3234561811 | H60: =IF(G60="","Sin número",IF(LEFT(G60,1)="3","Celular","Fijo")) -> Celular | I60: =IF(H60="Celular",HYPERLINK("https://wa.me/57"&G60,"Abrir chat"),"") -> Abrir chat | J60: Cra 52 # 46-68 L 327 | K60: Por contactar | M60: =IF(L60="","",L60+4) | O60: =IF(N60="","",INDEX(Planes!$B$4:$B$6,MATCH(N60,Planes!$A$4:$A$6,0))) | P60: Enviar mensaje 1 | R60: Sin confirmar | S60: =HYPERLINK("https://directorio-empresas.einforma.co/informacion-empresa/asados-tipicos-carbon-sas","Ver fuente") -> Ver fuente
A61: 60 | B61: Media | C61: Atlántico Peruano SAS | D61: Medellín | E61: El Poblado | F61: Restaurante peruano | G61: 3104225583 | H61: =IF(G61="","Sin número",IF(LEFT(G61,1)="3","Celular","Fijo")) -> Celular | I61: =IF(H61="Celular",HYPERLINK("https://wa.me/57"&G61,"Abrir chat"),"") -> Abrir chat | J61: Cra 33 # 7-55 | K61: Por contactar | M61: =IF(L61="","",L61+4) | O61: =IF(N61="","",INDEX(Planes!$B$4:$B$6,MATCH(N61,Planes!$A$4:$A$6,0))) | P61: Enviar mensaje 1 | R61: Sin confirmar | S61: =HYPERLINK("https://directorio-empresas.einforma.co/informacion-empresa/atlantico-peruano-sas","Ver fuente") -> Ver fuente
A62: 61 | B62: Media | C62: Bon Camarón Ceviche SAS | D62: Medellín | F62: Cevichería | G62: 3005944617 | H62: =IF(G62="","Sin número",IF(LEFT(G62,1)="3","Celular","Fijo")) -> Celular | I62: =IF(H62="Celular",HYPERLINK("https://wa.me/57"&G62,"Abrir chat"),"") -> Abrir chat | K62: Por contactar | M62: =IF(L62="","",L62+4) | O62: =IF(N62="","",INDEX(Planes!$B$4:$B$6,MATCH(N62,Planes!$A$4:$A$6,0))) | P62: Enviar mensaje 1 | R62: Sin confirmar | S62: =HYPERLINK("https://directorio-empresas.einforma.co/informacion-empresa/atlantico-peruano-sas","Ver fuente") -> Ver fuente
A63: 62 | B63: Media | C63: Café Cliché | D63: Medellín | E63: Laureles | F63: Restaurante café | G63: 3103684867 | H63: =IF(G63="","Sin número",IF(LEFT(G63,1)="3","Celular","Fijo")) -> Celular | I63: =IF(H63="Celular",HYPERLINK("https://wa.me/57"&G63,"Abrir chat"),"") -> Abrir chat | K63: Por contactar | M63: =IF(L63="","",L63+4) | O63: =IF(N63="","",INDEX(Planes!$B$4:$B$6,MATCH(N63,Planes!$A$4:$A$6,0))) | P63: Enviar mensaje 1b | R63: Domicilios por WhatsApp (guía de 2020) | S63: =HYPERLINK("https://medellinguru.com/laureles-with-domicilio/","Ver fuente") -> Ver fuente
A64: 63 | B64: Media | C64: Chapati Halal SAS | D64: Medellín | E64: El Poblado | F64: Restaurante | G64: 3045686852 | H64: =IF(G64="","Sin número",IF(LEFT(G64,1)="3","Celular","Fijo")) -> Celular | I64: =IF(H64="Celular",HYPERLINK("https://wa.me/57"&G64,"Abrir chat"),"") -> Abrir chat | J64: Cra 48 # 7-298 | K64: Por contactar | M64: =IF(L64="","",L64+4) | O64: =IF(N64="","",INDEX(Planes!$B$4:$B$6,MATCH(N64,Planes!$A$4:$A$6,0))) | P64: Enviar mensaje 1 | R64: Sin confirmar | S64: =HYPERLINK("https://directorio-empresas.einforma.co/informacion-empresa/chapati-halal-sas","Ver fuente") -> Ver fuente
A65: 64 | B65: Media | C65: Delivery and Delicius Sushi SAS | D65: Medellín | E65: El Poblado | F65: Sushi a domicilio | G65: 3112962649 | H65: =IF(G65="","Sin número",IF(LEFT(G65,1)="3","Celular","Fijo")) -> Celular | I65: =IF(H65="Celular",HYPERLINK("https://wa.me/57"&G65,"Abrir chat"),"") -> Abrir chat | J65: Cl 9A # 38-26 | K65: Por contactar | M65: =IF(L65="","",L65+4) | O65: =IF(N65="","",INDEX(Planes!$B$4:$B$6,MATCH(N65,Planes!$A$4:$A$6,0))) | P65: Enviar mensaje 1 | R65: Sin confirmar | S65: =HYPERLINK("https://www.informacolombia.com/directorio-empresas/informacion-empresa/roll-company-sas","Ver fuente") -> Ver fuente
A66: 65 | B66: Media | C66: El Rey Parrillero Laureles SAS | D66: Medellín | E66: Laureles | F66: Parrilla | G66: 3017915689 | H66: =IF(G66="","Sin número",IF(LEFT(G66,1)="3","Celular","Fijo")) -> Celular | I66: =IF(H66="Celular",HYPERLINK("https://wa.me/57"&G66,"Abrir chat"),"") -> Abrir chat | J66: Cra 73 Circular 3 # 30 | K66: Por contactar | M66: =IF(L66="","",L66+4) | O66: =IF(N66="","",INDEX(Planes!$B$4:$B$6,MATCH(N66,Planes!$A$4:$A$6,0))) | P66: Enviar mensaje 1 | R66: Sin confirmar | S66: =HYPERLINK("https://directorio-empresas.einforma.co/informacion-empresa/rey-parrillero-laureles-sas","Ver fuente") -> Ver fuente
A67: 66 | B67: Media | C67: Empanadas Las Calidosas del Centro SAS | D67: Medellín | E67: Centro | F67: Comida rápida | G67: 3216289188 | H67: =IF(G67="","Sin número",IF(LEFT(G67,1)="3","Celular","Fijo")) -> Celular | I67: =IF(H67="Celular",HYPERLINK("https://wa.me/57"&G67,"Abrir chat"),"") -> Abrir chat | J67: Cl 53 # 49-23 | K67: Por contactar | M67: =IF(L67="","",L67+4) | O67: =IF(N67="","",INDEX(Planes!$B$4:$B$6,MATCH(N67,Planes!$A$4:$A$6,0))) | P67: Enviar mensaje 1 | R67: Sin confirmar | S67: =HYPERLINK("https://www.informacolombia.com/directorio-empresas/informacion-empresa/empanadas-calidosas-centro-sas","Ver fuente") -> Ver fuente
A68: 67 | B68: Media | C68: Hanami SAS | D68: Medellín | E68: El Poblado | F68: Restaurante | G68: 3013381466 | H68: =IF(G68="","Sin número",IF(LEFT(G68,1)="3","Celular","Fijo")) -> Celular | I68: =IF(H68="Celular",HYPERLINK("https://wa.me/57"&G68,"Abrir chat"),"") -> Abrir chat | J68: Cl 10B # 35-8 | K68: Por contactar | M68: =IF(L68="","",L68+4) | O68: =IF(N68="","",INDEX(Planes!$B$4:$B$6,MATCH(N68,Planes!$A$4:$A$6,0))) | P68: Enviar mensaje 1 | R68: Sin confirmar | S68: =HYPERLINK("https://www.informacolombia.com/directorio-empresas/informacion-empresa/hanami-sas","Ver fuente") -> Ver fuente
A69: 68 | B69: Media | C69: Happy Grill Cocina SAS | D69: Medellín | F69: Comida rápida | G69: 3004050749 | H69: =IF(G69="","Sin número",IF(LEFT(G69,1)="3","Celular","Fijo")) -> Celular | I69: =IF(H69="Celular",HYPERLINK("https://wa.me/57"&G69,"Abrir chat"),"") -> Abrir chat | K69: Por contactar | M69: =IF(L69="","",L69+4) | O69: =IF(N69="","",INDEX(Planes!$B$4:$B$6,MATCH(N69,Planes!$A$4:$A$6,0))) | P69: Enviar mensaje 1 | R69: Sin confirmar | S69: =HYPERLINK("https://www.informacolombia.com/directorio-empresas/actividad/5619_OTROS-TIPOS-DE-EXPENDIO-DE-COMIDAS-PREPARADAS-N-C-P/localidad_medellin","Ver fuente") -> Ver fuente
A70: 69 | B70: Media | C70: Happy Wraps SAS | D70: Medellín | F70: Comida rápida | G70: 3174389371 | H70: =IF(G70="","Sin número",IF(LEFT(G70,1)="3","Celular","Fijo")) -> Celular | I70: =IF(H70="Celular",HYPERLINK("https://wa.me/57"&G70,"Abrir chat"),"") -> Abrir chat | J70: Cra 27D # 34A Sur-91 | K70: Por contactar | M70: =IF(L70="","",L70+4) | O70: =IF(N70="","",INDEX(Planes!$B$4:$B$6,MATCH(N70,Planes!$A$4:$A$6,0))) | P70: Enviar mensaje 1 | R70: Sin confirmar | S70: =HYPERLINK("https://www.informacolombia.com/directorio-empresas/informacion-empresa/jugosa-ltda","Ver fuente") -> Ver fuente
A71: 70 | B71: Media | C71: Kuipers Parrilla SAS | D71: Medellín | F71: Parrilla | G71: 3225169897 | H71: =IF(G71="","Sin número",IF(LEFT(G71,1)="3","Celular","Fijo")) -> Celular | I71: =IF(H71="Celular",HYPERLINK("https://wa.me/57"&G71,"Abrir chat"),"") -> Abrir chat | J71: Cl 115 # 64 | K71: Por contactar | M71: =IF(L71="","",L71+4) | O71: =IF(N71="","",INDEX(Planes!$B$4:$B$6,MATCH(N71,Planes!$A$4:$A$6,0))) | P71: Enviar mensaje 1 | R71: Sin confirmar | S71: =HYPERLINK("https://directorio-empresas.einforma.co/informacion-empresa/asados-tipicos-carbon-sas","Ver fuente") -> Ver fuente
A72: 71 | B72: Media | C72: La Casa del Alimento SAS | D72: Medellín | F72: Restaurante | G72: 3185878459 | H72: =IF(G72="","Sin número",IF(LEFT(G72,1)="3","Celular","Fijo")) -> Celular | I72: =IF(H72="Celular",HYPERLINK("https://wa.me/57"&G72,"Abrir chat"),"") -> Abrir chat | J72: Cra 87 # 45C-17 | K72: Por contactar | M72: =IF(L72="","",L72+4) | O72: =IF(N72="","",INDEX(Planes!$B$4:$B$6,MATCH(N72,Planes!$A$4:$A$6,0))) | P72: Enviar mensaje 1 | R72: Sin confirmar | S72: =HYPERLINK("https://www.informacolombia.com/directorio-empresas/informacion-empresa/casa-alimento-sas","Ver fuente") -> Ver fuente
A73: 72 | B73: Media | C73: La Ribera Restaurante SAS | D73: Medellín | F73: Restaurante | G73: 3017379330 | H73: =IF(G73="","Sin número",IF(LEFT(G73,1)="3","Celular","Fijo")) -> Celular | I73: =IF(H73="Celular",HYPERLINK("https://wa.me/57"&G73,"Abrir chat"),"") -> Abrir chat | K73: Por contactar | M73: =IF(L73="","",L73+4) | O73: =IF(N73="","",INDEX(Planes!$B$4:$B$6,MATCH(N73,Planes!$A$4:$A$6,0))) | P73: Enviar mensaje 1 | R73: Sin confirmar | S73: =HYPERLINK("https://directorio-empresas.einforma.co/informacion-empresa/ribera-restaurante-sas","Ver fuente") -> Ver fuente
A74: 73 | B74: Media | C74: Los Chamos Arepas Venezolanas y Algo Más SAS | D74: Medellín | E74: Laureles | F74: Arepería | G74: 3103773771 | H74: =IF(G74="","Sin número",IF(LEFT(G74,1)="3","Celular","Fijo")) -> Celular | I74: =IF(H74="Celular",HYPERLINK("https://wa.me/57"&G74,"Abrir chat"),"") -> Abrir chat | J74: Circular 5 # 70-30 | K74: Por contactar | M74: =IF(L74="","",L74+4) | O74: =IF(N74="","",INDEX(Planes!$B$4:$B$6,MATCH(N74,Planes!$A$4:$A$6,0))) | P74: Enviar mensaje 1 | R74: Sin confirmar | S74: =HYPERLINK("https://directorio-empresas.einforma.co/informacion-empresa/chamos-arepas-venezolanas-algo-mas-sas","Ver fuente") -> Ver fuente
A75: 74 | B75: Media | C75: Love Restaurant SAS | D75: Medellín | E75: Laureles | F75: Restaurante | G75: 3052247450 | H75: =IF(G75="","Sin número",IF(LEFT(G75,1)="3","Celular","Fijo")) -> Celular | I75: =IF(H75="Celular",HYPERLINK("https://wa.me/57"&G75,"Abrir chat"),"") -> Abrir chat | J75: Cl 33 # 74E-156 P 7 | K75: Por contactar | M75: =IF(L75="","",L75+4) | O75: =IF(N75="","",INDEX(Planes!$B$4:$B$6,MATCH(N75,Planes!$A$4:$A$6,0))) | P75: Enviar mensaje 1 | R75: Sin confirmar | S75: =HYPERLINK("https://www.informacolombia.com/directorio-empresas/informacion-empresa/love-restaurant-sas","Ver fuente") -> Ver fuente
A76: 75 | B76: Media | C76: Lu Mara Restaurante SAS | D76: Medellín | E76: Laureles | F76: Restaurante | G76: 3015383860 | H76: =IF(G76="","Sin número",IF(LEFT(G76,1)="3","Celular","Fijo")) -> Celular | I76: =IF(H76="Celular",HYPERLINK("https://wa.me/57"&G76,"Abrir chat"),"") -> Abrir chat | J76: Cl 33 # 83-02 | K76: Por contactar | M76: =IF(L76="","",L76+4) | O76: =IF(N76="","",INDEX(Planes!$B$4:$B$6,MATCH(N76,Planes!$A$4:$A$6,0))) | P76: Enviar mensaje 1 | R76: Sin confirmar | S76: =HYPERLINK("https://www.informacolombia.com/directorio-empresas/informacion-empresa/lu-mara-restaurante-sas","Ver fuente") -> Ver fuente
A77: 76 | B77: Media | C77: Makabro Salvaje SAS | D77: Medellín | E77: Laureles | F77: Restaurante | G77: 3183121016 | H77: =IF(G77="","Sin número",IF(LEFT(G77,1)="3","Celular","Fijo")) -> Celular | I77: =IF(H77="Celular",HYPERLINK("https://wa.me/57"&G77,"Abrir chat"),"") -> Abrir chat | J77: Cra 80 # 48B-40 | K77: Por contactar | M77: =IF(L77="","",L77+4) | O77: =IF(N77="","",INDEX(Planes!$B$4:$B$6,MATCH(N77,Planes!$A$4:$A$6,0))) | P77: Enviar mensaje 1 | R77: Sin confirmar | S77: =HYPERLINK("https://www.informacolombia.com/directorio-empresas/informacion-empresa/makabro-salvaje-sas","Ver fuente") -> Ver fuente
A78: 77 | B78: Media | C78: Mondongos Colombia SAS | D78: Medellín | E78: Belén | F78: Restaurante típico | G78: 3106423348 | H78: =IF(G78="","Sin número",IF(LEFT(G78,1)="3","Celular","Fijo")) -> Celular | I78: =IF(H78="Celular",HYPERLINK("https://wa.me/57"&G78,"Abrir chat"),"") -> Abrir chat | J78: Cra 70C # 3-43 | K78: Por contactar | M78: =IF(L78="","",L78+4) | O78: =IF(N78="","",INDEX(Planes!$B$4:$B$6,MATCH(N78,Planes!$A$4:$A$6,0))) | P78: Enviar mensaje 1 | R78: Sin confirmar | S78: =HYPERLINK("https://directorio-empresas.einforma.co/informacion-empresa/mondongos-colombia-sas","Ver fuente") -> Ver fuente
A79: 78 | B79: Media | C79: Mystic Foods SAS | D79: Medellín | E79: Laureles | F79: Restaurante | G79: 3178548254 | H79: =IF(G79="","Sin número",IF(LEFT(G79,1)="3","Celular","Fijo")) -> Celular | I79: =IF(H79="Celular",HYPERLINK("https://wa.me/57"&G79,"Abrir chat"),"") -> Abrir chat | J79: Cl 45F # 77A-61 | K79: Por contactar | M79: =IF(L79="","",L79+4) | O79: =IF(N79="","",INDEX(Planes!$B$4:$B$6,MATCH(N79,Planes!$A$4:$A$6,0))) | P79: Enviar mensaje 1 | R79: Sin confirmar | S79: =HYPERLINK("https://www.informacolombia.com/directorio-empresas/informacion-empresa/3-sibaritas-sas","Ver fuente") -> Ver fuente
A80: 79 | B80: Media | C80: Neo Gourmet Food SAS | D80: Medellín | F80: Restaurante | G80: 3137892487 | H80: =IF(G80="","Sin número",IF(LEFT(G80,1)="3","Celular","Fijo")) -> Celular | I80: =IF(H80="Celular",HYPERLINK("https://wa.me/57"&G80,"Abrir chat"),"") -> Abrir chat | K80: Por contactar | M80: =IF(L80="","",L80+4) | O80: =IF(N80="","",INDEX(Planes!$B$4:$B$6,MATCH(N80,Planes!$A$4:$A$6,0))) | P80: Enviar mensaje 1 | R80: Sin confirmar | S80: =HYPERLINK("https://www.informacolombia.com/directorio-empresas/actividad/560_ACTIVIDADES-DE-SERVICIOS-DE-COMIDAS-Y-BEBIDAS","Ver fuente") -> Ver fuente
A81: 80 | B81: Media | C81: Niku Cartagena SAS | D81: Medellín | E81: El Poblado | F81: Restaurante | G81: 3108338166 | H81: =IF(G81="","Sin número",IF(LEFT(G81,1)="3","Celular","Fijo")) -> Celular | I81: =IF(H81="Celular",HYPERLINK("https://wa.me/57"&G81,"Abrir chat"),"") -> Abrir chat | J81: Cl 12 # 31-85 | K81: Por contactar | M81: =IF(L81="","",L81+4) | O81: =IF(N81="","",INDEX(Planes!$B$4:$B$6,MATCH(N81,Planes!$A$4:$A$6,0))) | P81: Enviar mensaje 1 | R81: Sin confirmar | S81: =HYPERLINK("https://directorio-empresas.einforma.co/informacion-empresa/niku-cartagena-sas","Ver fuente") -> Ver fuente
A82: 81 | B82: Media | C82: Office Burger Family SAS | D82: Medellín | F82: Comida rápida | G82: 3005942872 | H82: =IF(G82="","Sin número",IF(LEFT(G82,1)="3","Celular","Fijo")) -> Celular | I82: =IF(H82="Celular",HYPERLINK("https://wa.me/57"&G82,"Abrir chat"),"") -> Abrir chat | J82: Cra 38 # 18-101 L 9723 | K82: Por contactar | M82: =IF(L82="","",L82+4) | O82: =IF(N82="","",INDEX(Planes!$B$4:$B$6,MATCH(N82,Planes!$A$4:$A$6,0))) | P82: Enviar mensaje 1 | R82: Sin confirmar | S82: =HYPERLINK("https://www.informacolombia.com/directorio-empresas/informacion-empresa/office-burger-family-sas","Ver fuente") -> Ver fuente
A83: 82 | B83: Media | C83: Ojalá Brunch | D83: Medellín | E83: El Poblado | F83: Brunch | G83: 3159163874 | H83: =IF(G83="","Sin número",IF(LEFT(G83,1)="3","Celular","Fijo")) -> Celular | I83: =IF(H83="Celular",HYPERLINK("https://wa.me/57"&G83,"Abrir chat"),"") -> Abrir chat | J83: Cra 43E # 11-46 | K83: Por contactar | M83: =IF(L83="","",L83+4) | O83: =IF(N83="","",INDEX(Planes!$B$4:$B$6,MATCH(N83,Planes!$A$4:$A$6,0))) | P83: Enviar mensaje 1b | R83: Menú en línea con pedidos a WhatsApp (ola.click) | S83: =HYPERLINK("https://ojala-brunch-2.ola.click/","Ver fuente") -> Ver fuente
A84: 83 | B84: Media | C84: Oni Medellín SAS | D84: Medellín | E84: El Poblado | F84: Restaurante | G84: 3246411797 | H84: =IF(G84="","Sin número",IF(LEFT(G84,1)="3","Celular","Fijo")) -> Celular | I84: =IF(H84="Celular",HYPERLINK("https://wa.me/57"&G84,"Abrir chat"),"") -> Abrir chat | J84: Cra 35 # 10B-80 L 105 | K84: Por contactar | M84: =IF(L84="","",L84+4) | O84: =IF(N84="","",INDEX(Planes!$B$4:$B$6,MATCH(N84,Planes!$A$4:$A$6,0))) | P84: Enviar mensaje 1 | R84: Sin confirmar | S84: =HYPERLINK("https://directorio-empresas.einforma.co/informacion-empresa/oni-medellin-sas","Ver fuente") -> Ver fuente
A85: 84 | B85: Media | C85: Operamos Restaurantes SAS | D85: Medellín | F85: Restaurante | G85: 3202342421 | H85: =IF(G85="","Sin número",IF(LEFT(G85,1)="3","Celular","Fijo")) -> Celular | I85: =IF(H85="Celular",HYPERLINK("https://wa.me/57"&G85,"Abrir chat"),"") -> Abrir chat | J85: Cra 35 # 29-02 Int 101 | K85: Por contactar | M85: =IF(L85="","",L85+4) | O85: =IF(N85="","",INDEX(Planes!$B$4:$B$6,MATCH(N85,Planes!$A$4:$A$6,0))) | P85: Enviar mensaje 1 | R85: Sin confirmar | S85: =HYPERLINK("https://www.informacolombia.com/directorio-empresas/informacion-empresa/operamos-restaurantes-sas","Ver fuente") -> Ver fuente
A86: 85 | B86: Media | C86: Opulencia SAS | D86: Medellín | F86: Restaurante | G86: 3104939221 | H86: =IF(G86="","Sin número",IF(LEFT(G86,1)="3","Celular","Fijo")) -> Celular | I86: =IF(H86="Celular",HYPERLINK("https://wa.me/57"&G86,"Abrir chat"),"") -> Abrir chat | J86: Cl 17 # 40B-185 | K86: Por contactar | M86: =IF(L86="","",L86+4) | O86: =IF(N86="","",INDEX(Planes!$B$4:$B$6,MATCH(N86,Planes!$A$4:$A$6,0))) | P86: Enviar mensaje 1 | R86: Sin confirmar | S86: =HYPERLINK("https://www.informacolombia.com/directorio-empresas/informacion-empresa/opulencia-sas","Ver fuente") -> Ver fuente
A87: 86 | B87: Media | C87: Osteria Local SAS | D87: Medellín | F87: Restaurante italiano | G87: 3183758418 | H87: =IF(G87="","Sin número",IF(LEFT(G87,1)="3","Celular","Fijo")) -> Celular | I87: =IF(H87="Celular",HYPERLINK("https://wa.me/57"&G87,"Abrir chat"),"") -> Abrir chat | K87: Por contactar | M87: =IF(L87="","",L87+4) | O87: =IF(N87="","",INDEX(Planes!$B$4:$B$6,MATCH(N87,Planes!$A$4:$A$6,0))) | P87: Enviar mensaje 1 | R87: Sin confirmar | S87: =HYPERLINK("https://www.informacolombia.com/directorio-empresas/actividad/I_ALOJAMIENTO-Y-SERVICIOS-DE-COMIDA/localidad_medellin","Ver fuente") -> Ver fuente
A88: 87 | B88: Media | C88: Pizzaiolo Colombia SAS | D88: Medellín | F88: Pizzería | G88: 3134095152 | H88: =IF(G88="","Sin número",IF(LEFT(G88,1)="3","Celular","Fijo")) -> Celular | I88: =IF(H88="Celular",HYPERLINK("https://wa.me/57"&G88,"Abrir chat"),"") -> Abrir chat | J88: Cra 37 # 8A-15 | K88: Por contactar | M88: =IF(L88="","",L88+4) | O88: =IF(N88="","",INDEX(Planes!$B$4:$B$6,MATCH(N88,Planes!$A$4:$A$6,0))) | P88: Enviar mensaje 1 | R88: Sin confirmar | S88: =HYPERLINK("https://www.informacolombia.com/directorio-empresas/informacion-empresa/pizzaiolo-colombia-sas","Ver fuente") -> Ver fuente
A89: 88 | B89: Media | C89: Pizzalas AC SAS | D89: Medellín | F89: Pizzería | G89: 3012108726 | H89: =IF(G89="","Sin número",IF(LEFT(G89,1)="3","Celular","Fijo")) -> Celular | I89: =IF(H89="Celular",HYPERLINK("https://wa.me/57"&G89,"Abrir chat"),"") -> Abrir chat | J89: Cra 73 # 98-88 | K89: Por contactar | M89: =IF(L89="","",L89+4) | O89: =IF(N89="","",INDEX(Planes!$B$4:$B$6,MATCH(N89,Planes!$A$4:$A$6,0))) | P89: Enviar mensaje 1 | R89: Sin confirmar | S89: =HYPERLINK("https://directorio-empresas.einforma.co/informacion-empresa/pizzalas-ac-sas","Ver fuente") -> Ver fuente
A90: 89 | B90: Media | C90: Pollos a la Brasa Mario de la América La 44 SAS | D90: Medellín | E90: La América | F90: Asadero | G90: 3104521433 | H90: =IF(G90="","Sin número",IF(LEFT(G90,1)="3","Celular","Fijo")) -> Celular | I90: =IF(H90="Celular",HYPERLINK("https://wa.me/57"&G90,"Abrir chat"),"") -> Abrir chat | J90: Cl 44 # 80-185 | K90: Por contactar | M90: =IF(L90="","",L90+4) | O90: =IF(N90="","",INDEX(Planes!$B$4:$B$6,MATCH(N90,Planes!$A$4:$A$6,0))) | P90: Enviar mensaje 1 | R90: Sin confirmar | S90: =HYPERLINK("https://www.informacolombia.com/directorio-empresas/informacion-empresa/pollos-brasa-mario-america-44-sas","Ver fuente") -> Ver fuente
A91: 90 | B91: Media | C91: Q'hubole Restaurante Bar | D91: Medellín | E91: San Javier | F91: Restaurante bar | G91: 3003657171 | H91: =IF(G91="","Sin número",IF(LEFT(G91,1)="3","Celular","Fijo")) -> Celular | I91: =IF(H91="Celular",HYPERLINK("https://wa.me/57"&G91,"Abrir chat"),"") -> Abrir chat | J91: Cra 99 # 47A-9 | K91: Por contactar | M91: =IF(L91="","",L91+4) | O91: =IF(N91="","",INDEX(Planes!$B$4:$B$6,MATCH(N91,Planes!$A$4:$A$6,0))) | P91: Enviar mensaje 1b | R91: Menú en línea con pedidos a WhatsApp (ola.click) | S91: =HYPERLINK("https://qhubole.ola.click/","Ver fuente") -> Ver fuente
A92: 91 | B92: Media | C92: Restaurante Chino Shenlong SAS | D92: Medellín | F92: Restaurante chino | G92: 3242312925 | H92: =IF(G92="","Sin número",IF(LEFT(G92,1)="3","Celular","Fijo")) -> Celular | I92: =IF(H92="Celular",HYPERLINK("https://wa.me/57"&G92,"Abrir chat"),"") -> Abrir chat | J92: Cra 31A # 102B-43 | K92: Por contactar | M92: =IF(L92="","",L92+4) | O92: =IF(N92="","",INDEX(Planes!$B$4:$B$6,MATCH(N92,Planes!$A$4:$A$6,0))) | P92: Enviar mensaje 1 | R92: Sin confirmar | S92: =HYPERLINK("https://www.informacolombia.com/directorio-empresas/informacion-empresa/restaurante-chino-shenlong-sas","Ver fuente") -> Ver fuente
A93: 92 | B93: Media | C93: Restaurante Gran Ching Hong Yun SAS | D93: Medellín | F93: Restaurante chino | G93: 3117582286 | H93: =IF(G93="","Sin número",IF(LEFT(G93,1)="3","Celular","Fijo")) -> Celular | I93: =IF(H93="Celular",HYPERLINK("https://wa.me/57"&G93,"Abrir chat"),"") -> Abrir chat | J93: Cl 37 # 88-65 Int 101 | K93: Por contactar | M93: =IF(L93="","",L93+4) | O93: =IF(N93="","",INDEX(Planes!$B$4:$B$6,MATCH(N93,Planes!$A$4:$A$6,0))) | P93: Enviar mensaje 1 | R93: Sin confirmar | S93: =HYPERLINK("https://www.informacolombia.com/directorio-empresas/informacion-empresa/restaurante-gran-ching-hong-yun-sas","Ver fuente") -> Ver fuente
A94: 93 | B94: Media | C94: Restaurante Las Panas SAS | D94: Medellín | E94: Guayabal | F94: Restaurante | G94: 3206914312 | H94: =IF(G94="","Sin número",IF(LEFT(G94,1)="3","Celular","Fijo")) -> Celular | I94: =IF(H94="Celular",HYPERLINK("https://wa.me/57"&G94,"Abrir chat"),"") -> Abrir chat | J94: Cra 51 # 8 Sur-18 | K94: Por contactar | M94: =IF(L94="","",L94+4) | O94: =IF(N94="","",INDEX(Planes!$B$4:$B$6,MATCH(N94,Planes!$A$4:$A$6,0))) | P94: Enviar mensaje 1 | R94: Sin confirmar | S94: =HYPERLINK("https://www.informacolombia.com/directorio-empresas/informacion-empresa/restaurante-panas-sas","Ver fuente") -> Ver fuente
A95: 94 | B95: Media | C95: Saludpan | D95: Medellín | E95: Laureles | F95: Restaurante vegetariano | G95: 3104281548 | H95: =IF(G95="","Sin número",IF(LEFT(G95,1)="3","Celular","Fijo")) -> Celular | I95: =IF(H95="Celular",HYPERLINK("https://wa.me/57"&G95,"Abrir chat"),"") -> Abrir chat | K95: Por contactar | M95: =IF(L95="","",L95+4) | O95: =IF(N95="","",INDEX(Planes!$B$4:$B$6,MATCH(N95,Planes!$A$4:$A$6,0))) | P95: Enviar mensaje 1b | R95: Domicilios por WhatsApp (guía de 2020) | S95: =HYPERLINK("https://medellinguru.com/laureles-with-domicilio/","Ver fuente") -> Ver fuente
A96: 95 | B96: Media | C96: Taco House Mexican Grill SAS | D96: Medellín | E96: El Poblado | F96: Restaurante mexicano | G96: 3114246481 | H96: =IF(G96="","Sin número",IF(LEFT(G96,1)="3","Celular","Fijo")) -> Celular | I96: =IF(H96="Celular",HYPERLINK("https://wa.me/57"&G96,"Abrir chat"),"") -> Abrir chat | J96: Cra 33 # 7-127 | K96: Por contactar | M96: =IF(L96="","",L96+4) | O96: =IF(N96="","",INDEX(Planes!$B$4:$B$6,MATCH(N96,Planes!$A$4:$A$6,0))) | P96: Enviar mensaje 1 | R96: Sin confirmar | S96: =HYPERLINK("https://directorio-empresas.einforma.co/informacion-empresa/taco-house-mexican-grill-sas","Ver fuente") -> Ver fuente
A97: 96 | B97: Media | C97: W Fuego Burger Inversiones SAS | D97: Medellín | F97: Comida rápida | G97: 3204731706 | H97: =IF(G97="","Sin número",IF(LEFT(G97,1)="3","Celular","Fijo")) -> Celular | I97: =IF(H97="Celular",HYPERLINK("https://wa.me/57"&G97,"Abrir chat"),"") -> Abrir chat | J97: Dg 29D # 9 Sur-110 | K97: Por contactar | M97: =IF(L97="","",L97+4) | O97: =IF(N97="","",INDEX(Planes!$B$4:$B$6,MATCH(N97,Planes!$A$4:$A$6,0))) | P97: Enviar mensaje 1 | R97: Sin confirmar | S97: =HYPERLINK("https://www.informacolombia.com/directorio-empresas/informacion-empresa/w-fuego-burger-inversiones-sas","Ver fuente") -> Ver fuente
A98: 97 | B98: Media | C98: Zacatecas | D98: Medellín | F98: Comida mexicana (cadena) | G98: 3108947678 | H98: =IF(G98="","Sin número",IF(LEFT(G98,1)="3","Celular","Fijo")) -> Celular | I98: =IF(H98="Celular",HYPERLINK("https://wa.me/57"&G98,"Abrir chat"),"") -> Abrir chat | K98: Por contactar | M98: =IF(L98="","",L98+4) | O98: =IF(N98="","",INDEX(Planes!$B$4:$B$6,MATCH(N98,Planes!$A$4:$A$6,0))) | P98: Enviar mensaje 1b | R98: Número de WhatsApp publicado (guía) | S98: =HYPERLINK("https://medellinguru.com/zacatecas/","Ver fuente") -> Ver fuente
A99: 98 | B99: Baja | C99: Cafe Coffee Beans | D99: Bello | F99: Café | G99: 3207893494 | H99: =IF(G99="","Sin número",IF(LEFT(G99,1)="3","Celular","Fijo")) -> Celular | I99: =IF(H99="Celular",HYPERLINK("https://wa.me/57"&G99,"Abrir chat"),"") -> Abrir chat | K99: Por contactar | M99: =IF(L99="","",L99+4) | O99: =IF(N99="","",INDEX(Planes!$B$4:$B$6,MATCH(N99,Planes!$A$4:$A$6,0))) | P99: Enviar mensaje 1 | R99: Sin confirmar | S99: =HYPERLINK("https://www.informacolombia.com/directorio-empresas/actividad/560_ACTIVIDADES-DE-SERVICIOS-DE-COMIDAS-Y-BEBIDAS/localidad_bello?qPg=2","Ver fuente") -> Ver fuente
A100: 99 | B100: Baja | C100: Chickenresto Bar Bello | D100: Bello | F100: Asadero / bar | G100: 3004892646 | H100: =IF(G100="","Sin número",IF(LEFT(G100,1)="3","Celular","Fijo")) -> Celular | I100: =IF(H100="Celular",HYPERLINK("https://wa.me/57"&G100,"Abrir chat"),"") -> Abrir chat | K100: Por contactar | M100: =IF(L100="","",L100+4) | O100: =IF(N100="","",INDEX(Planes!$B$4:$B$6,MATCH(N100,Planes!$A$4:$A$6,0))) | P100: Enviar mensaje 1 | R100: Sin confirmar | S100: =HYPERLINK("https://www.informacolombia.com/directorio-empresas/actividad/560_ACTIVIDADES-DE-SERVICIOS-DE-COMIDAS-Y-BEBIDAS/localidad_bello?qPg=2","Ver fuente") -> Ver fuente
...

Sheet Resumen
A1: Resumen de la prospección
A2: Se actualiza solo a medida que cambia la columna Estado en Restaurantes.
A4: Estado | B4: Restaurantes | C4: % del total
A5: Por contactar | B5: =COUNTIF(Restaurantes!$K$2:$K$153,A5) -> 152 | C5: =IF($B$13=0,0,B5/$B$13) -> 1
A6: Mensaje enviado | B6: =COUNTIF(Restaurantes!$K$2:$K$153,A6) -> 0 | C6: =IF($B$13=0,0,B6/$B$13) -> 0
A7: Respondió | B7: =COUNTIF(Restaurantes!$K$2:$K$153,A7) -> 0 | C7: =IF($B$13=0,0,B7/$B$13) -> 0
A8: Demo agendada | B8: =COUNTIF(Restaurantes!$K$2:$K$153,A8) -> 0 | C8: =IF($B$13=0,0,B8/$B$13) -> 0
A9: En prueba | B9: =COUNTIF(Restaurantes!$K$2:$K$153,A9) -> 0 | C9: =IF($B$13=0,0,B9/$B$13) -> 0
A10: Cliente | B10: =COUNTIF(Restaurantes!$K$2:$K$153,A10) -> 0 | C10: =IF($B$13=0,0,B10/$B$13) -> 0
A11: No interesado | B11: =COUNTIF(Restaurantes!$K$2:$K$153,A11) -> 0 | C11: =IF($B$13=0,0,B11/$B$13) -> 0
A12: Número errado | B12: =COUNTIF(Restaurantes!$K$2:$K$153,A12) -> 0 | C12: =IF($B$13=0,0,B12/$B$13) -> 0
A13: Total | B13: =COUNTA(Restaurantes!$C$2:$C$153) -> 152 | C13: =IF($B$13=0,0,B13/$B$13) -> 1
A15: Indicadores
A16: Contactados (todo menos Por contactar) | B16: =B13-B5 -> 0
A17: Tasa de respuesta | B17: =IF(B16=0,0,(B7+B8+B9+B10+B11)/B16) -> 0
A18: Demos, pruebas y clientes | B18: =B8+B9+B10 -> 0
A19: Clientes | B19: =B10 -> 0
A20: Ingreso mensual de clientes (COP) | B20: =SUMIFS(Restaurantes!$O$2:$O$153,Restaurantes!$K$2:$K$153,"Cliente") -> 0
A21: Seguimientos vencidos hoy | B21: =COUNTIFS(Restaurantes!$K$2:$K$153,"Mensaje enviado",Restaurantes!$M$2:$M$153,"<="&TODAY()) -> 0
A22: Restaurantes con celular | B22: =COUNTIF(Restaurantes!$H$2:$H$153,"Celular") -> 109
A23: Restaurantes en Medellín | B23: =COUNTIF(Restaurantes!$D$2:$D$153,"Medellín") -> 126
A24: Restaurantes en Bello | B24: =COUNTIF(Restaurantes!$D$2:$D$153,"Bello") -> 26
A25: Prioridad alta (ya venden por WhatsApp) | B25: =COUNTIF(Restaurantes!$B$2:$B$153,"Alta") -> 48
A26: Prioridad media | B26: =COUNTIF(Restaurantes!$B$2:$B$153,"Media") -> 49
A27: Prioridad baja | B27: =COUNTIF(Restaurantes!$B$2:$B$153,"Baja") -> 55

Sheet Planes
A1: Planes y precios
A3: Plan | B3: Mensualidad (COP) | C3: Instalación (COP) | D3: Impresora opcional (COP) | E3: Incluye
A4: Básico | B4: 350000 | C4: 200000 | D4: No disponible | E4: Bot de pedidos (menú, catálogo, audios), IA del administrador, domicilios por zona y efectivo. Transferencias las confirma una persona.
A5: Avanzado | B5: 450000 | C5: 200000 | D5: 350000 | E5: Todo lo del Básico, y el bot lee el comprobante de transferencia. Impresora de comandas opcional.
A6: Premium | B6: 550000 | C6: 200000 | D6: 350000 | E6: Todo lo del Avanzado, más domiciliarios con liquidación y cierre diario, estadísticas, consultas de pedidos y Excel.
A9: Fuente: tabla de planes del panel, enviada por el dueño del producto (28-oct-2026).

Sheet Mensajes
A1: Mensajes para WhatsApp (uno por uno, desde el número de ventas)
A3: 1. Primer mensaje | B3: Buenas, ¿hablo con el restaurante {nombre}? Mi nombre es {su nombre}, le escribo desde Medellín. Hicimos un asistente para el WhatsApp de restaurantes: le contesta a los clientes, toma el pedido completo con la dirección y le calcula el domicilio según el barrio. El menú del día se carga mandando una foto. ¿Le puedo mostrar cómo funciona?
A4: 1b. Ya venden por WhatsApp | B4: Buenas, ¿hablo con {nombre}? Mi nombre es {su nombre}. Vi que reciben los pedidos por WhatsApp. A la hora del almuerzo, ¿quién contesta todos esos mensajes? Tenemos un asistente que los contesta solo: toma el pedido, confirma la dirección, calcula el domicilio, revisa el comprobante de la transferencia y le manda la comanda a la cocina. Usted solo revisa. ¿Le muestro cómo quedaría con su menú?
A5: 2. Si hacen domicilios | B5: Hola, vi que {nombre} hace domicilios por WhatsApp. A la hora del almuerzo se llenan los mensajes y alguien tiene que contestar uno por uno, ¿cierto? Tenemos un asistente que contesta, toma el pedido y se lo deja listo. Si quiere, la comanda le sale impresa en la cocina. ¿Le gustaría verlo funcionando con su propio menú?
A6: 3. Seguimiento (una sola vez) | B6: Hola de nuevo. Le escribí la semana pasada por el asistente de pedidos para WhatsApp. Si quiere, le preparo una prueba con el menú de {nombre} de esta semana y usted mismo le escribe como si fuera un cliente. ¿Le sirve?
A7: 4. Cuando dicen que sí | B7: Listo, con mucho gusto. Mándeme una foto del menú de hoy y los barrios a donde hace domicilios con el valor de cada uno. Con eso se lo dejo armado y le paso el número para que pruebe.
A8: 5. Llamada a un fijo | B8: Buenas, ¿con el restaurante {nombre}? Le habla {su nombre}. ¿Ustedes reciben pedidos por WhatsApp? Le pregunto porque tenemos un asistente que los contesta y toma el pedido completo. ¿Me regala un celular para mandarle cómo funciona?
A9: Si dicen que no | B9: Listo, no le vuelvo a escribir. Que le vaya muy bien.

Sheet Cómo usar
A1: Cómo usar esta hoja
A3: 1. Empiece por la prioridad Alta: son restaurantes que ya reciben pedidos por WhatsApp (tienen menú en línea que manda el pedido a WhatsApp, o publican su WhatsApp para domicilios). Media: tipo de negocio que suele vender a domicilio y con celular, pero sin prueba de que use WhatsApp. Baja: cafés, bares, restaurantes de mesa o solo con fijo.
A4: 2. Las celdas amarillas de Restaurantes son las que usted llena: Estado, Primer contacto, Plan de interés, Próxima acción y Notas. Lo demás se calcula solo.
A5: 3. Ejemplo: escribe por WhatsApp a un restaurante → Estado = Mensaje enviado, Primer contacto = 28/10/2026. La columna Seguimiento muestra 01/11/2026 y se pone en rojo cuando ya toca escribir de nuevo.
A6: 4. La columna WhatsApp abre el chat directo con el celular del restaurante. Los fijos (604...) se llaman: use el mensaje 5 de la pestaña Mensajes.
A7: 5. Cuando alguien escoja un plan, márquelo en Plan de interés; la mensualidad sale de la pestaña Planes.
A8: 6. Si el número no existe o es de otro negocio, Estado = Número errado.
A9: 7. Para no arriesgar el número de ventas: 30 a 40 mensajes al día, uno por uno, nunca desde el número del bot.
A10: 8. Origen de los datos: páginas de menú en línea de cada restaurante (ola.click), directorios de empresas registradas (informacolombia.com y einforma.co) y guías de restaurantes con domicilio (medellinguru.com, varias de 2020). Son registros públicos que pueden estar desactualizados; la columna Fuente lleva a la ficha de cada uno.
A11: 9. Para conseguir más restaurantes: python3 ventas/buscar_restaurantes.py --solo-contactables (necesita acceso a OpenStreetMap).
